nemesis/__init__.py
nemesis/console.py
nemesis/exceptions.py
nemesis/resources/__init__.py
nemesis/resources/elasticsearch/__init__.py
nemesis/resources/elasticsearch/alias.py
nemesis/resources/elasticsearch/index.py
nemesis/resources/elasticsearch/index_template.py
nemesis/resources/elasticsearch/ingest_pipeline.py
nemesis/resources/elasticsearch/logstash_pipeline.py
nemesis/resources/elasticsearch/querydsl.py
nemesis/resources/elasticsearch/security.py
nemesis/resources/elasticsearch/transform.py
nemesis/resources/elasticsearch/watcher.py
nemesis/schemas/__init__.py
nemesis/schemas/elasticsearch/__init__.py
nemesis/schemas/elasticsearch/alias.py
nemesis/schemas/elasticsearch/index.py
nemesis/schemas/elasticsearch/index_template.py
nemesis/schemas/elasticsearch/ingest_pipeline.py
nemesis/schemas/elasticsearch/logstash_pipeline.py
nemesis/schemas/elasticsearch/querydsl.py
nemesis/schemas/elasticsearch/security.py
nemesis/schemas/elasticsearch/transform.py
nemesis/schemas/elasticsearch/watcher.py
nemesis/scripts/__init__.py
nemesis/scripts/nemesis.py
nemesis/templates/__init__.py
nemesis/templates/__nemesis__.py.tmpl
nemesis/tests/__init__.py
nemesis/tests/resources/elasticsearch/test_index.py
nemesis/tests/resources/elasticsearch/test_index_template.py
nemesis/tests/resources/elasticsearch/test_ingest_pipeline.py
nemesis/tests/resources/elasticsearch/test_logstash_pipeline.py
nemesis/tests/resources/elasticsearch/test_query_dsl.py
nemesis/tests/resources/elasticsearch/test_security.py
nemesis/tests/resources/elasticsearch/test_transform.py
nemesis/tests/resources/elasticsearch/test_watcher.py
nemesis/tests/test_init.py
nemesis/tests/test_utils.py
nemesis/utils.py
nemesis-0.0.9.dist-info/entry_points.txt
nemesis-0.0.9.dist-info/LICENSE
nemesis-0.0.9.dist-info/WHEEL
nemesis-0.0.9.dist-info/METADATA
nemesis-0.0.9.dist-info/RECORD
