Metadata-Version: 2.1
Name: nemesis
Version: 0.0.9
Summary: Tool for managing Elasticsearch resources as code
Home-page: https://github.com/fxdgear/nemesis
Author: Nick Lang
Author-email: nick@nicklang.com
Requires-Python: >=3.6,<4.0
Classifier: Programming Language :: Python :: 3
Classifier: Programming Language :: Python :: 3.10
Classifier: Programming Language :: Python :: 3.6
Classifier: Programming Language :: Python :: 3.7
Classifier: Programming Language :: Python :: 3.8
Classifier: Programming Language :: Python :: 3.9
Provides-Extra: docs
Requires-Dist: Click (>=7.1,<7.2)
Requires-Dist: Sphinx (>=4.4.0,<5.0.0); extra == "docs"
Requires-Dist: dacite (>=1.6.0,<2.0.0)
Requires-Dist: deepdiff (>=5.6.0,<6.0.0)
Requires-Dist: elasticsearch (>=7.15.2,<8.0.0)
Requires-Dist: marshmallow (>=3.14.1,<4.0.0)
Requires-Dist: python-dateutil (>=2.8.2,<3.0.0)
Requires-Dist: pytz (>=2021.3,<2022.0)
Requires-Dist: requests (>=2.26.0,<3.0.0)
Requires-Dist: rich (>=10.14.0,<11.0.0)
Requires-Dist: sphinx-rtd-theme (>=1.0.0,<2.0.0)
